ashok_ll/__init__.py
ashok_ll/node.py
ashok_ll/operations.py
ashok_ll-0.1.2.dist-info/METADATA
ashok_ll-0.1.2.dist-info/WHEEL
ashok_ll-0.1.2.dist-info/top_level.txt
ashok_ll-0.1.2.dist-info/RECORD
